ucsdcape/__init__.py
ucsdcape/__main__.py
ucsdcape/capedata.py
ucsd_cape-0.3.0.dist-info/LICENSE
ucsd_cape-0.3.0.dist-info/METADATA
ucsd_cape-0.3.0.dist-info/WHEEL
ucsd_cape-0.3.0.dist-info/top_level.txt
ucsd_cape-0.3.0.dist-info/RECORD
