Metadata-Version: 2.1
Name: ucsd-cape
Version: 0.3.0
Summary: Web scraper for the UCSD Course and Professor Evaluations (CAPE) website.
Author-email: Jacob Lee <Jacob.J.Lee@outlook.com>
License: MIT License
Project-URL: homepage, https://github.com/JacobLee23/UCSD-CAPE
Classifier: Development Status :: 3 - Alpha
Classifier: License :: OSI Approved :: MIT License
Classifier: Natural Language :: English
Classifier: Operating System :: OS Independent
Classifier: Programming Language :: JavaScript
Classifier: Programming Language :: Python
Classifier: Programming Language :: Python :: 3
Classifier: Programming Language :: Python :: 3.6
Classifier: Programming Language :: Python :: 3.7
Classifier: Programming Language :: Python :: 3.8
Classifier: Programming Language :: Python :: 3.9
Classifier: Programming Language :: Python :: 3.10
Classifier: Programming Language :: Python :: 3.11
Classifier: Topic :: Software Development
Requires-Python: >=3.6
License-File: LICENSE
